geodrive/__init__.py
geodrive-0.1.0.dist-info/WHEEL
geodrive-0.1.0.dist-info/METADATA
geodrive-0.1.0.dist-info/RECORD
