Metadata-Version: 2.3
Name: geodrive
Version: 0.1.0
Summary: Universal SDK for rover programming
Requires-Python: >=3.9
